mysearch-1.1.dist-info/WHEEL
mysearch-1.1.dist-info/metadata.json
mysearch-1.1.dist-info/RECORD
mysearch-1.1.dist-info/DESCRIPTION.rst
mysearch-1.1.dist-info/METADATA
mysearch-1.1.dist-info/top_level.txt
mysearch/onion.py
mysearch/__init__.py
mysearch/mysearch.tac
mysearch/mysearch.py
mysearch/version.txt
mysearch/backends.py
mysearch/utils.py
mysearch/ext_libs/__init__.py
mysearch/ext_libs/service_identity/__init__.py
mysearch/ext_libs/service_identity/_attrs.py
mysearch/ext_libs/service_identity/_common.py
mysearch/ext_libs/service_identity/pyopenssl.py
mysearch/ext_libs/service_identity/_compat.py
mysearch/templates/index.html
mysearch/templates/header.html
mysearch/templates/mysearch.html
mysearch/templates/redirect.html
mysearch/templates/opensearchdescription.xml
mysearch/static/plus_icon.png
mysearch/static/favicon64.png
mysearch/static/favicon-openstreetmap.ico
mysearch/static/mysearch.css
mysearch/static/search_icon.png
mysearch/static/favicon-wikipedia.ico
mysearch/static/favicon-google.ico
mysearch/static/google_images_layout.js
mysearch/static/favicon.ico
mysearch/static/jquery-1.7.2.min.js
