Metadata-Version: 2.0
Name: mysearch
Version: 1.1
Summary: MySearch engine
Home-page: http://codingteam.net/project/mysearch
Author: Tuxicoman
Author-email: debian@jesuislibre.net
License: AGPL
Platform: UNKNOWN
